[
  {
    "id": 10579,
    "name": "Portland Int'l Airport",
    "direction": "Eastbound (To Hillsboro)",
    "lat": 45.587584,
    "long": -122.5931
  },
  {
    "id": 10577,
    "name": "Mt Hood Ave",
    "direction": "Southbound (To Hillsboro)",
    "lat": 45.5768610212536,
    "long": -122.567140829383
  },
  {
    "id": 10575,
    "name": "Cascades",
    "direction": "Eastbound (To Hillsboro)",
    "lat": 45.5720751580038,
    "long": -122.557700297686
  },
  {
    "id": 10573,
    "name": "Parkrose/Sumner TC",
    "direction": "Southbound (To Hillsboro)",
    "lat": 45.5588291962123,
    "long": -122.565860703069
  },
  {
    "id": 14250,
    "name": "Gateway North",
    "direction": "Southbound (To Hillsboro)",
    "lat": 45.53219379164804,
    "long": -122.56374188813442
  },
  {
    "id": 8371,
    "name": "NE 82nd Ave",
    "direction": "Westbound (To Hillsboro)",
    "lat": 45.5334782038965,
    "long": -122.578437295634
  },
  {
    "id": 8372,
    "name": "NE 60th Ave",
    "direction": "Westbound (To Hillsboro)",
    "lat": 45.5284911659404,
    "long": -122.603341898276
  },
  {
    "id": 8373,
    "name": "Hollywood/NE 42nd Ave",
    "direction": "Westbound (To Hillsboro)",
    "lat": 45.5329565531532,
    "long": -122.621366792078
  },
  {
    "id": 8374,
    "name": "Lloyd Center/NE 11th Ave",
    "direction": "Westbound (To Hillsboro)",
    "lat": 45.5301463713758,
    "long": -122.654334508265
  },
  {
    "id": 8375,
    "name": "NE 7th Ave",
    "direction": "Westbound (To Hillsboro)",
    "lat": 45.53015,
    "long": -122.658277
  },
  {
    "id": 8376,
    "name": "Convention Center",
    "direction": "Westbound (To Hillsboro)",
    "lat": 45.530137848543,
    "long": -122.662539549115
  },
  {
    "id": 8377,
    "name": "Rose Quarter TC",
    "direction": "Westbound (To Hillsboro)",
    "lat": 45.5302353512818,
    "long": -122.66555734012
  },
  {
    "id": 8378,
    "name": "Old Town/Chinatown",
    "direction": "Southbound (To Hillsboro)",
    "lat": 45.5246953346089,
    "long": -122.671466795694
  },
  {
    "id": 8379,
    "name": "Skidmore Fountain",
    "direction": "Southbound (To Hillsboro)",
    "lat": 45.5228727583101,
    "long": -122.671390260638
  },
  {
    "id": 8380,
    "name": "Oak/SW 1st Ave",
    "direction": "Southbound (To Hillsboro)",
    "lat": 45.5198597205757,
    "long": -122.672522992326
  },
  {
    "id": 8381,
    "name": "Morrison/SW 3rd Ave",
    "direction": "Westbound (To Hillsboro)",
    "lat": 45.5181811277907,
    "long": -122.675385866199
  },
  {
    "id": 8383,
    "name": "Pioneer Square North",
    "direction": "Westbound (To Hillsboro)",
    "lat": 45.5192530913679,
    "long": -122.679474777158
  },
  {
    "id": 8384,
    "name": "Galleria/SW 10th Ave",
    "direction": "Westbound (To Hillsboro)",
    "lat": 45.5199099188694,
    "long": -122.681918753514
  },
  {
    "id": 9757,
    "name": "Providence Park",
    "direction": "Westbound (To Hillsboro)",
    "lat": 45.521832999998,
    "long": -122.68981599998
  },
  {
    "id": 10117,
    "name": "Goose Hollow/SW Jefferson St",
    "direction": "Westbound (To Hillsboro)",
    "lat": 45.5182356297709,
    "long": -122.694089417009
  },
  {
    "id": 10121,
    "name": "Washington Park",
    "direction": "Westbound (To Hillsboro)",
    "lat": 45.510661324633,
    "long": -122.717244395707
  },
  {
    "id": 9624,
    "name": "Sunset TC",
    "direction": "Westbound (To Hillsboro)",
    "lat": 45.5103834911766,
    "long": -122.781299103305
  },
  {
    "id": 9818,
    "name": "Beaverton TC",
    "direction": "Southbound (To Hillsboro)",
    "lat": 45.4913303686551,
    "long": -122.801723195359
  },
  {
    "id": 9823,
    "name": "Beaverton Central",
    "direction": "Westbound (To Hillsboro)",
    "lat": 45.4904249498466,
    "long": -122.807441381743
  },
  {
    "id": 9825,
    "name": "Millikan Way",
    "direction": "Westbound (To Hillsboro)",
    "lat": 45.4954211232751,
    "long": -122.821805929724
  },
  {
    "id": 9819,
    "name": "Beaverton Creek",
    "direction": "Northbound (To Hillsboro)",
    "lat": 45.5005843177686,
    "long": -122.833325448821
  },
  {
    "id": 9827,
    "name": "Merlo Rd/SW 158th Ave",
    "direction": "Westbound (To Hillsboro)",
    "lat": 45.505398884013,
    "long": -122.842423579432
  },
  {
    "id": 9829,
    "name": "Elmonica/SW 170th Ave",
    "direction": "Westbound (To Hillsboro)",
    "lat": 45.5101335586911,
    "long": -122.851732209868
  },
  {
    "id": 9832,
    "name": "Willow Creek/SW 185th Ave TC",
    "direction": "Westbound (To Hillsboro)",
    "lat": 45.517375259177,
    "long": -122.870517927838
  },
  {
    "id": 9833,
    "name": "Quatama",
    "direction": "Westbound (To Hillsboro)",
    "lat": 45.5233194229215,
    "long": -122.889131375697
  },
  {
    "id": 9836,
    "name": "Orenco",
    "direction": "Westbound (To Hillsboro)",
    "lat": 45.5302983625332,
    "long": -122.916198426399
  },
  {
    "id": 9840,
    "name": "Hawthorn Farm",
    "direction": "Westbound (To Hillsboro)",
    "lat": 45.5299206129352,
    "long": -122.931119810485
  },
  {
    "id": 9837,
    "name": "Hillsboro Airport/Fairgrounds",
    "direction": "Terminus (Hillsboro)",
    "lat": 45.5269236271043,
    "long": -122.946499150393
  }
]
